setup.py
GRPgraph/DATA_TIME.py
GRPgraph/SONG.py
GRPgraph/__init__.py
GRPgraph/py2D.py
GRPgraph/py3D.py
GRPgraph/test.py
GRPgraph.egg-info/PKG-INFO
GRPgraph.egg-info/SOURCES.txt
GRPgraph.egg-info/dependency_links.txt
GRPgraph.egg-info/not-zip-safe
GRPgraph.egg-info/requires.txt
GRPgraph.egg-info/top_level.txt