Metadata-Version: 1.0
Name: GRPgraph
Version: 12.8
Summary: small and compact graphick distributions
Home-page: UNKNOWN
Author: UNKNOWN
Author-email: pvana621@gmail.com
License: UNKNOWN
Platform: UNKNOWN
